annoyance/__init__.py
annoyance/_core/_SpotifyAnnoy.py
annoyance/_core/__init__.py
annoyance/_core/_idx_funcs/__init__.py
annoyance/_core/_idx_funcs/_build.py
annoyance/_core/_idx_funcs/_load.py
annoyance/_core/_idx_funcs/_query.py
annoyance/_core/_idx_funcs/_save.py
annoyance/_interactive_funcs/__init__.py
annoyance/_interactive_funcs/_binominal_test_train_assignment.py
annoyance/_interactive_funcs/_count_obs_neighbors.py
annoyance/_interactive_funcs/_create_label_mask.py
annoyance/_interactive_funcs/_use_X.py
annoyance/_map/__init__.py
annoyance/_map/_annotate_adata_bool_idx.py
annoyance/_map/_iterative_kNN_smoothing.py
annoyance/_map/_kNN_map_source_to_target.py
annoyance-0.0.18.dist-info/LICENSE
annoyance-0.0.18.dist-info/METADATA
annoyance-0.0.18.dist-info/WHEEL
annoyance-0.0.18.dist-info/top_level.txt
annoyance-0.0.18.dist-info/RECORD
