Metadata-Version: 2.1
Name: annoyance
Version: 0.0.18
Summary: annoyance - single-cell AnnData wrapper of Spotify's Annoy library.
Home-page: 
Author: Michael E. Vinyard - Harvard University - Massachussetts General Hospital - Broad Institute of MIT and Harvard
Author-email: mvinyard@broadinstitute.org
License: MIT
Classifier: Development Status :: 2 - Pre-Alpha
Classifier: Programming Language :: Python :: 3.7
Classifier: Intended Audience :: Science/Research
Classifier: Topic :: Scientific/Engineering :: Bio-Informatics
Requires-Python: >3.7.0
License-File: LICENSE
Requires-Dist: annoy (>=1.17.0)
Requires-Dist: anndata (>=0.8)
Requires-Dist: pandas (>=1.4.4)
Requires-Dist: pydk (>=0.0.54)
